{
  "id": "wallpaperflare-sklxq",
  "title": "Bistro building digital wallpaper, BioShock, Rapture, screen shot HD wallpaper",
  "thumbnail_url": "https://c4.wallpaperflare.com/wallpaper/422/207/662/bioshock-rapture-screen-shot-video-games-wallpaper-preview.jpg",
  "detail_url": "https://www.wallpaperflare.com/bistro-building-digital-wallpaper-bioshock-rapture-screen-shot-wallpaper-sklxq",
  "download_url": "https://r4.wallpaperflare.com/wallpaper/422/207/662/bioshock-rapture-screen-shot-video-games-wallpaper-f72e08a7b1e1bccafe529300d9614a0a.jpg",
  "tags": [
    "BioShock",
    "Rapture",
    "screen shot",
    "video games",
    "underwater",
    "submarine",
    "illuminated",
    "night",
    "built structure",
    "architecture",
    "building exterior",
    "glass - material",
    "text",
    "city",
    "no people",
    "transparent",
    "window",
    "western script",
    "transportation",
    "communication",
    "building",
    "reflection",
    "mode of transportation",
    "outdoors",
    "neon",
    "water",
    "skyscraper",
    "bistro",
    "digital",
    "wallpaper",
    "HD wallpapers",
    "PC wallpapers",
    "mobile wallpapers",
    "tablet wallpapers",
    "HD desktop",
    "free download",
    "1080P",
    "2K",
    "4K",
    "5K"
  ]
}