{
  "id": "wallpaperflare-hvwry",
  "title": "monkey, gun, artwork, tie, suits, one animal, indoors, portrait HD wallpaper",
  "thumbnail_url": "https://c4.wallpaperflare.com/wallpaper/858/362/564/monkey-gun-artwork-tie-wallpaper-preview.jpg",
  "detail_url": "https://www.wallpaperflare.com/monkey-gun-artwork-tie-suits-one-animal-indoors-portrait-wallpaper-hvwry",
  "download_url": "https://r4.wallpaperflare.com/wallpaper/858/362/564/monkey-gun-artwork-tie-wallpaper-c779aa0bc6aa95257c2dd89048472923.jpg",
  "tags": [
    "monkey",
    "gun",
    "artwork",
    "tie",
    "suits",
    "one animal",
    "indoors",
    "portrait",
    "looking at camera",
    "front view",
    "mammal",
    "necktie",
    "well-dressed",
    "suit",
    "gray",
    "menswear",
    "studio shot",
    "men",
    "business",
    "gray background",
    "people",
    "humor",
    "fun",
    "HD wallpapers",
    "PC wallpapers",
    "mobile wallpapers",
    "tablet wallpapers",
    "HD desktop",
    "free download",
    "1080P",
    "2K",
    "4K",
    "5K"
  ]
}