{
  "id": "wallpaperflare-pbauc",
  "title": "female sniper wallpaper, digital art, artwork, gun, fantasy art HD wallpaper",
  "thumbnail_url": "https://c4.wallpaperflare.com/wallpaper/814/182/423/digital-art-artwork-gun-fantasy-art-wallpaper-preview.jpg",
  "detail_url": "https://www.wallpaperflare.com/female-sniper-wallpaper-digital-art-artwork-gun-fantasy-art-wallpaper-pbauc",
  "download_url": "https://r4.wallpaperflare.com/wallpaper/814/182/423/digital-art-artwork-gun-fantasy-art-wallpaper-5960d8ad41da4dab46e7b82fa08116ed.jpg",
  "tags": [
    "digital art",
    "artwork",
    "gun",
    "fantasy art",
    "futuristic",
    "girls with guns",
    "one person",
    "holding",
    "weapon",
    "aiming",
    "rifle",
    "sport",
    "indoors",
    "adult",
    "full length",
    "skill",
    "real people",
    "young adult",
    "standing",
    "concentration",
    "nature",
    "lifestyles",
    "female",
    "sniper",
    "wallpaper",
    "HD wallpapers",
    "PC wallpapers",
    "mobile wallpapers",
    "tablet wallpapers",
    "HD desktop",
    "free download",
    "1080P",
    "2K",
    "4K",
    "5K"
  ]
}