{
  "id": "wallpaperflare-forz",
  "title": "Abstract 3D Art, Art 3D Digital Abstract  HD, Art Abstract Dance  Desktop HD wallpaper",
  "thumbnail_url": "https://c4.wallpaperflare.com/wallpaper/706/560/977/abstract-3d-art-art-3d-digital-abstract-hd-art-abstract-dance-desktop-artworks-wallpaper-preview.jpg",
  "detail_url": "https://www.wallpaperflare.com/abstract-3d-art-art-3d-digital-abstract-hd-art-abstract-dance-desktop-wallpaper-forz",
  "download_url": "https://r4.wallpaperflare.com/wallpaper/706/560/977/abstract-3d-art-art-3d-digital-abstract-hd-art-abstract-dance-desktop-artworks-wallpaper-c5e9a242b0cc933b4a1d542a6969b0e6.jpg",
  "tags": [
    "Abstract 3D Art",
    "Art 3D Digital Abstract  HD",
    "Art Abstract Dance  Desktop",
    "artworks",
    "colourful paints",
    "cool images",
    "drawings",
    "illustration",
    "japanese art",
    "illuminated",
    "architecture",
    "night",
    "built structure",
    "window",
    "lighting equipment",
    "creativity",
    "building exterior",
    "motion",
    "glass - material",
    "decoration",
    "animal representation",
    "art and craft",
    "incidental people",
    "representation",
    "reflection",
    "transparent",
    "city",
    "building",
    "HD wallpapers",
    "PC wallpapers",
    "mobile wallpapers",
    "tablet wallpapers",
    "HD desktop",
    "free download",
    "1080P",
    "2K",
    "4K",
    "5K"
  ]
}