{
  "id": "wallpaperflare-pbttz",
  "title": "person wearing black robe surrounded by skulls painting, Zdzisław Beksiński HD wallpaper",
  "thumbnail_url": "https://c4.wallpaperflare.com/wallpaper/282/266/335/zdzisław-beksiński-artwork-dark-wallpaper-preview.jpg",
  "detail_url": "https://www.wallpaperflare.com/person-wearing-black-robe-surrounded-by-skulls-painting-zdzisław-beksiński-wallpaper-pbttz",
  "download_url": "https://c4.wallpaperflare.com/wallpaper/282/266/335/zdzisław-beksiński-artwork-dark-wallpaper-preview.jpg",
  "tags": [
    "Zdzisław Beksiński",
    "artwork",
    "dark",
    "architecture",
    "group of people",
    "people",
    "real people",
    "religion",
    "crowd",
    "built structure",
    "belief",
    "day",
    "representation",
    "outdoors",
    "history",
    "spirituality",
    "art and craft",
    "animal wildlife",
    "group",
    "person",
    "wearing",
    "black",
    "robe",
    "surrounded",
    "skulls",
    "painting",
    "HD wallpapers",
    "PC wallpapers",
    "mobile wallpapers",
    "tablet wallpapers",
    "HD desktop",
    "free download",
    "1080P",
    "2K",
    "4K",
    "5K"
  ]
}