{
  "id": "wallpaperflare-qhidi",
  "title": "Naruto Tobi wallpaper, mask, Akatsuki, Uchiha, Madara, one person HD wallpaper",
  "thumbnail_url": "https://c4.wallpaperflare.com/wallpaper/527/725/231/mask-naruto-naruto-akatsuki-wallpaper-preview.jpg",
  "detail_url": "https://www.wallpaperflare.com/naruto-tobi-wallpaper-mask-akatsuki-uchiha-madara-one-person-wallpaper-qhidi",
  "download_url": "https://r4.wallpaperflare.com/wallpaper/527/725/231/mask-naruto-naruto-akatsuki-wallpaper-fb826a5206928da9301d25e6f26420f9.jpg",
  "tags": [
    "mask",
    "naruto",
    "Akatsuki",
    "Uchiha",
    "Madara",
    "one person",
    "studio shot",
    "rear view",
    "lifestyles",
    "indoors",
    "clothing",
    "portrait",
    "real people",
    "copy space",
    "headshot",
    "waist up",
    "holding",
    "leisure activity",
    "adult",
    "men",
    "warm clothing",
    "hat",
    "winter",
    "hood",
    "scarf",
    "hairstyle",
    "black background",
    "hood - clothing",
    "obscured face",
    "vector",
    "backgrounds",
    "illustration",
    "people",
    "computer Graphic",
    "symbol",
    "abstract",
    "spirituality",
    "ideas",
    "creativity",
    "art",
    "tobi",
    "wallpaper",
    "HD wallpapers",
    "PC wallpapers",
    "mobile wallpapers",
    "tablet wallpapers",
    "HD desktop",
    "free download",
    "1080P",
    "2K",
    "4K",
    "5K"
  ]
}