{
  "id": "wallpaperflare-ytbxc",
  "title": "artwork, illustration, digital art, fan art, drawing, Sciamano240 HD wallpaper",
  "thumbnail_url": "https://c4.wallpaperflare.com/wallpaper/432/807/723/artwork-illustration-digital-art-fan-art-drawing-hd-wallpaper-preview.jpg",
  "detail_url": "https://www.wallpaperflare.com/artwork-illustration-digital-art-fan-art-drawing-sciamano240-wallpaper-ytbxc",
  "download_url": "https://r4.wallpaperflare.com/wallpaper/432/807/723/artwork-illustration-digital-art-fan-art-drawing-hd-wallpaper-3a26753361ec6d87b0df26b794f01849.jpg",
  "tags": [
    "artwork",
    "illustration",
    "digital art",
    "fan art",
    "drawing",
    "Sciamano240",
    "video games",
    "video game girls",
    "video game characters",
    "Akali(League of Legends)",
    "League of Legends",
    "belly",
    "HD wallpapers",
    "PC wallpapers",
    "mobile wallpapers",
    "tablet wallpapers",
    "HD desktop",
    "free download",
    "1080P",
    "2K",
    "4K",
    "5K"
  ]
}