{
  "id": "wallpaperflare-qfpvi",
  "title": "Naruto Uchiha Madara wallpaper, anime boys, real people, clothing HD wallpaper",
  "thumbnail_url": "https://c4.wallpaperflare.com/wallpaper/60/426/326/uchiha-madara-anime-boys-anime-wallpaper-preview.jpg",
  "detail_url": "https://www.wallpaperflare.com/naruto-uchiha-madara-wallpaper-anime-boys-real-people-clothing-wallpaper-qfpvi",
  "download_url": "https://r4.wallpaperflare.com/wallpaper/60/426/326/uchiha-madara-anime-boys-anime-wallpaper-026162a02da64eebcaa832b5108849f2.jpg",
  "tags": [
    "Uchiha Madara",
    "anime boys",
    "anime",
    "real people",
    "clothing",
    "day",
    "people",
    "high angle view",
    "outdoors",
    "men",
    "lifestyles",
    "human body part",
    "nature",
    "adult",
    "shoe",
    "women",
    "leisure activity",
    "togetherness",
    "standing",
    "sunlight",
    "uniform",
    "naruto",
    "uchiha",
    "madara",
    "wallpaper",
    "HD wallpapers",
    "PC wallpapers",
    "mobile wallpapers",
    "tablet wallpapers",
    "HD desktop",
    "free download",
    "1080P",
    "2K",
    "4K",
    "5K"
  ]
}